trialts/__init__.py
trialts/trialt.py
trialt-0.0.1.dist-info/LICENSE
trialt-0.0.1.dist-info/METADATA
trialt-0.0.1.dist-info/WHEEL
trialt-0.0.1.dist-info/top_level.txt
trialt-0.0.1.dist-info/RECORD
