Metadata-Version: 2.1
Name: trialt
Version: 0.0.1
Summary: This is trialt - trialt trialt trialt
Home-page: https://gitee.com/wind619/trialt.git
Author: WindFog
Author-email: wind_fog@163.com
License: UNKNOWN
Platform: UNKNOWN
License-File: LICENSE
